penguin_tamer/__init__.py
penguin_tamer/__main__.py
penguin_tamer/arguments.py
penguin_tamer/cli.py
penguin_tamer/command_executor.py
penguin_tamer/config_manager.py
penguin_tamer/debug.py
penguin_tamer/default_config.yaml
penguin_tamer/dialog_input.py
penguin_tamer/error_handlers.py
penguin_tamer/i18n.py
penguin_tamer/i18n_content.py
penguin_tamer/llm_client.py
penguin_tamer/logger.py
penguin_tamer/prompts.py
penguin_tamer/settings_overview.py
penguin_tamer/system_info.py
penguin_tamer/text_utils.py
penguin_tamer/themes.py
penguin_tamer/demo_system/__init__.py
penguin_tamer/demo_system/config_demo.yaml
penguin_tamer/demo_system/manager.py
penguin_tamer/demo_system/models.py
penguin_tamer/demo_system/player.py
penguin_tamer/demo_system/recorder.py
penguin_tamer/llm_clients/__init__.py
penguin_tamer/llm_clients/base.py
penguin_tamer/llm_clients/factory.py
penguin_tamer/llm_clients/mistral_client.py
penguin_tamer/llm_clients/openai_client.py
penguin_tamer/llm_clients/openrouter_client.py
penguin_tamer/llm_clients/pollinations_client.py
penguin_tamer/llm_clients/stream_processor.py
penguin_tamer/locales/__init__.py
penguin_tamer/locales/ru.json
penguin_tamer/locales/template_locale.json
penguin_tamer/menu/__init__.py
penguin_tamer/menu/config_menu.py
penguin_tamer/menu/dialogs.py
penguin_tamer/menu/info_panel.py
penguin_tamer/menu/intro_screen.py
penguin_tamer/menu/provider_manager.py
penguin_tamer/menu/provider_utils.py
penguin_tamer/menu/styles.tcss
penguin_tamer/menu/widgets.py
penguin_tamer/menu/locales/__init__.py
penguin_tamer/menu/locales/help_content_en.py
penguin_tamer/menu/locales/help_content_ru.py
penguin_tamer/menu/locales/menu_i18n.py
penguin_tamer/menu/locales/ru.json
penguin_tamer/utils/__init__.py
penguin_tamer/utils/descriptors.py
penguin_tamer/utils/lazy_import.py
penguin_tamer-0.9.2.dist-info/METADATA
penguin_tamer-0.9.2.dist-info/WHEEL
penguin_tamer-0.9.2.dist-info/entry_points.txt
penguin_tamer-0.9.2.dist-info/top_level.txt
penguin_tamer-0.9.2.dist-info/RECORD
