Metadata-Version: 2.4
Name: penguin-tamer
Version: 0.9.2
Summary: Penguin Tamer - AI-powered terminal assistant for Linux systems
Author-email: Andrey Bochkarev <andrey.bch.1976@gmail.com>
License-Expression: MIT
Project-URL: Homepage, https://github.com/Vivatist/penguin-tamer
Project-URL: Bug Reports, https://github.com/Vivatist/penguin-tamer/issues
Project-URL: Source, https://github.com/Vivatist/penguin-tamer
Keywords: ai,terminal,console,bash,automation,penguin,tamer
Classifier: Development Status :: 4 - Beta
Classifier: Environment :: Console
Classifier: Intended Audience :: Developers
Classifier: Intended Audience :: System Administrators
Classifier: Operating System :: OS Independent
Classifier: Programming Language :: Python :: 3
Classifier: Programming Language :: Python :: 3.11
Classifier: Programming Language :: Python :: 3.12
Classifier: Topic :: System :: Systems Administration
Classifier: Topic :: Utilities
Requires-Python: >=3.11
Requires-Dist: certifi==2025.8.3
Requires-Dist: charset-normalizer==3.4.3
Requires-Dist: idna==3.10
Requires-Dist: markdown-it-py==3.0.0
Requires-Dist: mdurl==0.1.2
Requires-Dist: platformdirs==4.4.0
Requires-Dist: Pygments==2.19.2
Requires-Dist: requests==2.32.5
Requires-Dist: rich==14.1.0
Requires-Dist: urllib3==2.5.0
Requires-Dist: openai==1.108.0
Requires-Dist: PyYAML==6.0.2
Requires-Dist: inquirer==3.4.0
Requires-Dist: prompt-toolkit==3.0.52
Requires-Dist: textual>=0.47.0
Requires-Dist: sseclient-py==1.8.0
